verifiNN/__init__.py
verifiNN/examples.py
verifiNN/verifier.py
verifiNN/algorithms/__init__.py
verifiNN/models/__init__.py
verifiNN/models/network.py
verifiNN/utils/__init__.py
verifiNN/utils/utils.py
verifiNN-0.0.0.dev10.dist-info/METADATA
verifiNN-0.0.0.dev10.dist-info/WHEEL
verifiNN-0.0.0.dev10.dist-info/top_level.txt
verifiNN-0.0.0.dev10.dist-info/RECORD
